[
  {
    "league": "F1",
    "sport": "모터스포츠",
    "team_name": "맥라렌",
    "home_city": "Woking",
    "home_stadium": "McLaren Technology Center",
    "founded_year": 1963,
    "style_tags": [
      "Historic",
      "Champions",
      "Papaya",
      "Resurgent",
      "WokingBase",
      "Legacy",
      "SennaProstEra",
      "EngineeringExcellence",
      "NextGenTalent",
      "AggressiveDevelopment",
      "OperationalStrength",
      "MercedesPower",
      "HighStandards",
      "ZakBrownLeadership",
      "ConstructorsWinners"
    ],
    "scores": {
      "strength": 10,
      "money": 8,
      "star_power": 9,
      "attack_style": 7,
      "underdog_feel": 7,
      "fan_passion": 9,
      "tradition": 10
    },
    "meta_description": "모터스포츠에서 가장 오랜 역사를 가진 팀 중 하나로, 2024년 26년 만에 컨스트럭터 챔피언십 우승을 차지하며 화려하게 부활한 팀입니다. 에어튼 세나와 알랭 프로스트 등 전설적인 드라이버들을 배출했으며, 현재는 랜도 노리스와 오스카 피아스트리와 같은 젊은 인재들을 바탕으로 강력한 개발력을 앞세워 레드불과 페라리를 제치고 현 F1 그리드에서 가장 강력한 전력을 구축하고 있습니다. 역사와 혁신, 그리고 '파파야' 오렌지 컬러로 대변되는 팬덤을 자랑합니다."
  },
  {
    "league": "F1",
    "sport": "모터스포츠",
    "team_name": "메르세데스",
    "home_city": "브랙클리",
    "home_stadium": null,
    "founded_year": 1954,
    "style_tags": [
      "SilverArrows",
      "Dynasty",
      "GermanManufacturer",
      "HybridDominance",
      "TechnicalExcellence",
      "LewisHamilton",
      "TotoWolff",
      "RecordBreakers",
      "PrecisionEngineering",
      "CalculatedStrategy",
      "MotorsportHeritage",
      "Resilient",
      "WorldChampions",
      "BrackleyBase",
      "PostTurboEra"
    ],
    "scores": {
      "strength": 8,
      "money": 10,
      "star_power": 10,
      "attack_style": 9,
      "underdog_feel": 1,
      "fan_passion": 9,
      "tradition": 10
    },
    "meta_description": "메르세데스는 1954년 F1에 데뷔한 독일의 명문 팀이자, 현대 F1에서 가장 성공적인 팀 중 하나입니다. 루이스 해밀턴과 함께 터보 하이브리드 시대(2014-2021)에 8년 연속 컨스트럭터 챔피언십을 차지하는 전무후무한 기록을 세웠습니다. '실버 애로우'로 알려진 이 팀은 막강한 자본력과 뛰어난 기술력, 그리고 토토 볼프의 리더십을 바탕으로 2022년 규정 변경 이후 겪고 있는 부진을 딛고 다시 한번 정상을 노리고 있습니다."
  },
  {
    "league": "F1",
    "sport": "모터스포츠",
    "team_name": "레드불 레이싱",
    "home_city": "Milton Keynes",
    "home_stadium": null,
    "founded_year": 2005,
    "style_tags": [
      "Dominance",
      "Aggressive",
      "High-Aero",
      "Adrian Newey",
      "Energy Drink",
      "Young Driver Focus",
      "Championship Winners",
      "Strategic Acumen",
      "Boundary Pushing",
      "Financial Power",
      "Max Verstappen",
      "Controversial",
      "Innovation",
      "Chassis Excellence",
      "Ruthless Efficiency"
    ],
    "scores": {
      "strength": 10,
      "money": 10,
      "star_power": 10,
      "attack_style": 9,
      "underdog_feel": 1,
      "fan_passion": 9,
      "tradition": 4
    },
    "meta_description": "에너지 드링크 거대 기업이 설립한 F1 팀으로, 2010년대와 2020년대에 걸쳐 두 차례의 압도적인 황금기를 구가했다. 당대 최고의 엔지니어 에이드리언 뉴이의 천재성을 바탕으로 최강의 섀시를 자랑하며, 막스 페르스타펜을 필두로 공격적인 드라이버와 전략을 선호한다. 모터스포츠계의 현역 최강팀이자 압도적인 자본력을 바탕으로 트렌드를 선도하는 'F1의 거인'이다."
  },
  {
    "league": "F1",
    "sport": "모터스포츠",
    "team_name": "레이싱 불스",
    "home_city": "파엔차, 밀턴 케인즈",
    "home_stadium": null,
    "founded_year": 2006,
    "style_tags": [
      "Junior_Team",
      "Driver_Development",
      "Red_Bull_Ecosystem",
      "Midfield_Contender",
      "Opportunistic_Wins",
      "Faenza_Base",
      "Frequent_Driver_Swaps",
      "Talent_Incubator",
      "Honda_Engine_Partner",
      "Underdog_Spirit",
      "Aggressive_Strategy",
      "High_Variance_Performance",
      "Youthful_Lineup",
      "Rebranded_Identity",
      "Component_Sharing"
    ],
    "scores": {
      "strength": 5,
      "money": 7,
      "star_power": 6,
      "attack_style": 6,
      "underdog_feel": 9,
      "fan_passion": 5,
      "tradition": 4
    },
    "meta_description": "레드불 그룹 소유의 F1 팀으로, 2006년 스쿠데리아 토로 로쏘로 시작하여 알파타우리, 그리고 현재의 레이싱 불스까지 이어져 온 유서 깊은 드라이버 육성 팀입니다. 세바스찬 베텔, 막스 페르스타펜 등 미래의 월드 챔피언을 배출한 인큐베이터로 명성이 높습니다. 보통 중위권(미드필드)에 위치하며, 피에르 가슬리의 2020년 우승 등 혼란스러운 레이스에서 종종 대형 이변을 일으키는 예측 불가능한 도전자 이미지가 강합니다."
  },
  {
    "league": "F1",
    "sport": "모터스포츠",
    "team_name": "페라리",
    "home_city": "마라넬로",
    "home_stadium": "피오라노 서킷",
    "founded_year": 1929,
    "style_tags": [
      "Historical",
      "Scuderia",
      "Tifosi",
      "Legacy",
      "PrancingHorse",
      "Grandeur",
      "Maranello",
      "Red",
      "ItalianPride",
      "FlawedStrategy",
      "HighPressure",
      "ChampionshipChasers",
      "StarMagnet",
      "EngineFocus",
      "Rollercoaster"
    ],
    "scores": {
      "strength": 8,
      "money": 10,
      "star_power": 10,
      "attack_style": 9,
      "underdog_feel": 1,
      "fan_passion": 10,
      "tradition": 10
    },
    "meta_description": "모터스포츠 역사상 가장 위대한 이름이자 유일하게 F1 창설 이래 모든 시즌에 참가한 살아있는 전설. 페라리는 수많은 드라이버 및 컨스트럭터 타이틀 기록을 보유하고 있으며, 티포시(Tifosi)로 불리는 세계 최대의 열정적인 팬덤을 자랑한다. 최근 수년간 우승권의 압박감과 전략적 실수, 조직 문화 문제 등으로 인해 우승 기회를 놓치는 경우가 잦았으나, 여전히 최고 수준의 자본력과 스타성을 바탕으로 챔피언 자리를 되찾기 위해 끊임없이 도전하고 있다."
  },
  {
    "league": "F1",
    "sport": "모터스포츠",
    "team_name": "하스",
    "home_city": "Kannapolis, North Carolina",
    "home_stadium": null,
    "founded_year": 2014,
    "style_tags": [
      "AmericanUnderdog",
      "FerrariBTeam",
      "ScrappyFighter",
      "CNCManufacturer",
      "GuentherSteinerLegacy",
      "HighVariance",
      "Opportunistic",
      "TireStruggles",
      "BudgetCapChallenges",
      "DramaticDebut",
      "PolePositionShocker",
      "MidfieldStrivers",
      "DriveToSurviveStar",
      "USARacingEntry",
      "ChaosThemed"
    ],
    "scores": {
      "strength": 4,
      "money": 3,
      "star_power": 6,
      "attack_style": 7,
      "underdog_feel": 9,
      "fan_passion": 6,
      "tradition": 2
    },
    "meta_description": "하스 F1 팀은 2016년에 F1에 데뷔한 최초의 미국 팀입니다. 강력한 자본력 대신 페라리와의 기술 파트너십(B-팀 모델)을 통해 효율적인 운영을 추구합니다. 구단주 진 하스의 CNC 기계 회사 하스 오토메이션의 이름을 따왔으며, 2018년 컨스트럭터 챔피언십 5위를 기록하며 최고의 시즌을 보냈습니다. 귈터 슈타이너 전 감독의 'Drive to Survive' 출연으로 전 세계적인 인지도를 얻었으며, 종종 예산 및 타이어 관리 문제로 어려움을 겪지만 케빈 마그누센의 폴 포지션과 같은 놀라운 반란을 일으키는 전형적인 언더독 팀입니다."
  },
  {
    "league": "F1",
    "sport": "모터스포츠",
    "team_name": "알핀",
    "home_city": "앙스톤(영국) & 비리샤티용(프랑스)",
    "home_stadium": null,
    "founded_year": 2021,
    "style_tags": [
      "FrenchHeritage",
      "MidfieldBattler",
      "StrategicShift",
      "InternalTurmoil",
      "PiastriSaga",
      "EnstoneLegacy",
      "PowerUnitDeficit",
      "InconsistentPace",
      "ControversialLeadership",
      "LongTermProject",
      "DriverDrama",
      "RenaultRoots",
      "FutureFocused",
      "TechnicalStruggles",
      "DoublePodiumMoments"
    ],
    "scores": {
      "strength": 4,
      "money": 8,
      "star_power": 7,
      "attack_style": 6,
      "underdog_feel": 7,
      "fan_passion": 3,
      "tradition": 9
    },
    "meta_description": "르노 그룹의 스포츠카 브랜드 홍보를 위해 2021년 창단된 프랑스 국적의 워크스팀입니다. 베네통과 르노의 우승 역사를 잇는 긴 헤리티지를 가졌으나, 최근 몇 년간 고질적인 파워 유닛 성능 부족과 드라이버 이적, 팀 수뇌부 교체 등의 내부 혼란을 겪으며 중위권에서 고군분투하고 있습니다. 2026시즌부터 메르세데스 엔진을 사용하며 재도약을 노리고 있습니다."
  },
  {
    "league": "F1",
    "sport": "모터스포츠",
    "team_name": "애스턴 마틴",
    "home_city": "Silverstone",
    "home_stadium": "Silverstone Circuit (Campus)",
    "founded_year": 1913,
    "style_tags": [
      "BritishRacingGreen",
      "HighInvestment",
      "Challenger",
      "LawrenceStroll",
      "StateOfTheArtFacility",
      "AdrianNeweyEffect",
      "FernandoAlonso",
      "VeteranStar",
      "DevelopmentalStruggle",
      "LuxuryHeritage",
      "Ambition",
      "RapidAscent",
      "MidfieldAspirant",
      "HondaWorksTeam",
      "AggressiveRecruitment"
    ],
    "scores": {
      "strength": 6,
      "money": 9,
      "star_power": 8,
      "attack_style": 7,
      "underdog_feel": 8,
      "fan_passion": 7,
      "tradition": 8
    },
    "meta_description": "2021년 F1에 복귀한 유서 깊은 영국 스포츠카 브랜드. 구 레이싱 포인트를 인수하여 로렌스 스트롤 구단주 아래 막대한 자본력으로 신규 공장 및 풍동 건설, 아드리안 뉴이 등 최고 인재 영입에 공격적으로 투자하고 있다. 페르난도 알론소라는 노련한 스타 드라이버를 앞세워 2023년 시즌 초반 놀라운 성적을 거두며 단숨에 챔피언십 경쟁자로 발돋움했다. 현재는 중상위권의 강팀이지만, 2026년 혼다와의 파트너십을 통해 명실상부한 우승 후보로 도약하는 것을 목표로 한다."
  },
  {
    "league": "F1",
    "sport": "모터스포츠",
    "team_name": "윌리엄스 레이싱",
    "home_city": "그로브 (Grove)",
    "home_stadium": "그로브 공장",
    "founded_year": 1977,
    "style_tags": [
      "Legacy",
      "Heritage",
      "StrugglingGiant",
      "Underdog",
      "Resilience",
      "ChampionshipHistory",
      "FrankWilliamsVision",
      "LowBudgetAchiever",
      "EngineeringProwess",
      "RecentRebuild",
      "PrivateerSpirit",
      "DriverDevelopment",
      "MercedesPowerUnit",
      "SpeedTrapKing",
      "BritishInstitution"
    ],
    "scores": {
      "strength": 5,
      "money": 7,
      "star_power": 9,
      "attack_style": 7,
      "underdog_feel": 9,
      "fan_passion": 9,
      "tradition": 10
    },
    "meta_description": "윌리엄스 레이싱은 F1 역사상 세 번째로 오래된 팀이자 1980년대와 90년대 황금기를 이끈 명문입니다. 고(故) 프랭크 윌리엄스 경의 불굴의 투지로 유명하며, 아일톤 세나, 나이젤 만셀 등 수많은 챔피언을 배출했습니다. 비록 최근 몇 년간 하위권에 머물렀으나, 새로운 구단주 체제 아래에서 강력한 '도전자'의 이미지를 가지고 명가 재건을 꿈꾸고 있습니다. 2023년 7위, 2024년 9위 등 중위권 복귀를 위해 분투 중입니다."
  },
  {
    "league": "F1",
    "sport": "모터스포츠",
    "team_name": "자우버",
    "home_city": "힌윌, 스위스",
    "home_stadium": "힌윌 본사",
    "founded_year": 1993,
    "style_tags": [
      "Privateer",
      "Talent Scout",
      "Hinwil Legacy",
      "BMW Era",
      "Financial Resilience",
      "Audi Works Team",
      "Pragmatic Racer",
      "Midfield Maestro",
      "Opportunistic Points",
      "Swiss Engineering",
      "Underdog Spirit",
      "Pay Driver Necessity",
      "Ferrari Customer",
      "Wind Tunnel Pioneers",
      "Future Focused"
    ],
    "scores": {
      "strength": 2,
      "money": 8,
      "star_power": 7,
      "attack_style": 3,
      "underdog_feel": 9,
      "fan_passion": 6,
      "tradition": 7
    },
    "meta_description": "자우버는 1993년 F1에 데뷔한 스위스 프라이빗 팀입니다. 키미 라이코넨, 샤를 르클레르 등 수많은 스타 드라이버를 발굴한 '인재 육성소'로 명성이 높습니다. 만성적인 재정난과 기복에도 불구하고 끈질기게 그리드를 지켜왔으나, 최근 몇 년간은 최하위권에 머물렀습니다. 하지만 2026년 아우디의 워크스 팀으로 전환이 확정되면서 막대한 자본력과 함께 반전을 준비하고 있는, F1 그리드의 대표적인 도전자 팀입니다."
  }
]